guacamole/test_core.py
guacamole/__init__.py
guacamole/core.py
guacamole/recipes/cmd.py
guacamole/recipes/__init__.py
guacamole/ingredients/test_cmdtree.py
guacamole/ingredients/cmdtree.py
guacamole/ingredients/argparse.py
guacamole/ingredients/test_ansi.py
guacamole/ingredients/__init__.py
guacamole/ingredients/ansi.py
guacamole/ingredients/crash.py
guacamole-0.9.1.dist-info/RECORD
guacamole-0.9.1.dist-info/metadata.json
guacamole-0.9.1.dist-info/top_level.txt
guacamole-0.9.1.dist-info/DESCRIPTION.rst
guacamole-0.9.1.dist-info/WHEEL
guacamole-0.9.1.dist-info/pbr.json
guacamole-0.9.1.dist-info/METADATA
guacamole-0.9.1.dist-info/zip-safe
